tdrn/Tdrn.py
tdrn/__init__.py
tdrn/creat.py
Tdrd-0.0.1.dist-info/METADATA
Tdrd-0.0.1.dist-info/WHEEL
Tdrd-0.0.1.dist-info/top_level.txt
Tdrd-0.0.1.dist-info/RECORD
